pyrcb2/__init__.py
pyrcb2/accounts.py
pyrcb2/astdio.py
pyrcb2/decorators.py
pyrcb2/events.py
pyrcb2/grapheme_break_db.py
pyrcb2/graphemes.py
pyrcb2/itypes.py
pyrcb2/messages.py
pyrcb2/numerics.py
pyrcb2/pyrcb2.py
pyrcb2/sasl.py
pyrcb2/utils.py
pyrcb2-0.6.2.dist-info/LICENSE
pyrcb2-0.6.2.dist-info/METADATA
pyrcb2-0.6.2.dist-info/WHEEL
pyrcb2-0.6.2.dist-info/top_level.txt
pyrcb2-0.6.2.dist-info/RECORD
