Metadata-Version: 2.1
Name: pyrcb2
Version: 0.6.2
Summary: An asyncio-based IRC bot library.
Home-page: https://github.com/taylordotfish/pyrcb2
Author: taylor.fish
Author-email: contact@taylor.fish
License: GNU Lesser General Public License v3 or later (LGPLv3+)
Keywords: irc bot asyncio
Platform: UNKNOWN
Classifier: Development Status :: 4 - Beta
Classifier: Intended Audience :: Developers
Classifier: Topic :: Internet
Classifier: License :: OSI Approved :: GNU Lesser General Public License v3 or later (LGPLv3+)
Classifier: Operating System :: OS Independent
Classifier: Programming Language :: Python :: 3
Classifier: Programming Language :: Python :: 3.7
Classifier: Programming Language :: Python :: 3.8
Classifier: Programming Language :: Python :: 3.9
Requires-Python: >=3.7
